{
  "data": [
    {
      "x": [
        859.447,
        857.613,
        854.28,
        851.28,
        846.28,
        841.113,
        836.613,
        831.947,
        827.78,
        824.113,
        820.613,
        815.613,
        810.28,
        805.78,
        799.78,
        793.947,
        788.447,
        782.113,
        774.78,
        768.613,
        762.947,
        757.78,
        753.613,
        749.447,
        745.78,
        744.947,
        745.113,
        747.447,
        751.447,
        754.947,
        758.613,
        764.28,
        770.78,
        777.78,
        783.28,
        789.78,
        795.28,
        799.28,
        804.28,
        808.28,
        811.447,
        816.113,
        819.78,
        823.78,
        829.28,
        834.113,
        838.947,
        843.947,
        847.947,
        852.28,
        856.447,
        859.113,
        860.78
      ],
      "y": [
        88.362,
        86.529,
        84.529,
        82.862,
        81.529,
        81.529,
        82.195,
        83.529,
        85.529,
        88.195,
        91.029,
        94.862,
        98.529,
        101.195,
        103.862,
        105.862,
        107.529,
        109.362,
        110.529,
        112.029,
        113.695,
        116.362,
        118.529,
        121.029,
        123.362,
        125.362,
        127.362,
        127.529,
        126.529,
        124.695,
        121.695,
        118.362,
        117.029,
        115.862,
        114.529,
        112.862,
        111.195,
        109.695,
        107.695,
        105.362,
        103.029,
        99.029,
        96.029,
        93.195,
        89.529,
        86.695,
        85.362,
        85.029,
        85.695,
        86.862,
        88.695,
        90.195,
        90.529
      ]
    },
    {
      "x": [
        1194.121,
        1192.788,
        1190.788,
        1188.121,
        1185.621,
        1181.121,
        1175.955,
        1171.621,
        1166.288,
        1160.455,
        1154.955,
        1148.788,
        1142.788,
        1135.955,
        1130.288,
        1124.955,
        1118.288,
        1112.621,
        1107.121,
        1104.121,
        1100.621,
        1097.121,
        1093.455,
        1089.121,
        1084.621,
        1080.288,
        1076.788,
        1074.121,
        1072.621,
        1072.455,
        1074.955,
        1077.955,
        1081.955,
        1085.621,
        1090.455,
        1093.955,
        1096.121,
        1100.621,
        1105.121,
        1109.788,
        1113.288,
        1119.955,
        1125.121,
        1132.455,
        1138.455,
        1143.455,
        1149.788,
        1155.955,
        1163.455,
        1168.955,
        1174.621,
        1180.121,
        1184.621,
        1188.788,
        1190.121,
        1191.455,
        1192.621,
        1194.455,
        1198.121,
        1195.288
      ],
      "y": [
        138.748,
        135.748,
        132.582,
        130.582,
        128.915,
        126.748,
        125.415,
        124.748,
        124.748,
        124.915,
        125.248,
        125.582,
        125.748,
        126.082,
        126.415,
        127.415,
        128.748,
        130.582,
        132.915,
        134.748,
        137.415,
        140.082,
        143.415,
        147.748,
        150.748,
        152.915,
        155.415,
        157.915,
        159.415,
        161.582,
        162.415,
        162.415,
        161.082,
        158.748,
        155.582,
        152.415,
        149.915,
        146.082,
        142.748,
        139.415,
        137.248,
        134.915,
        133.748,
        132.415,
        131.582,
        130.748,
        130.082,
        129.415,
        128.915,
        129.248,
        130.582,
        131.915,
        133.748,
        136.248,
        137.748,
        140.082,
        142.915,
        143.915,
        144.082,
        141.248
      ]
    },
    {
      "x": [
        1399.264,
        1400.597,
        1400.264,
        1399.597,
        1397.264,
        1394.264,
        1390.93,
        1387.93,
        1385.43,
        1383.097,
        1381.097,
        1379.597,
        1378.43,
        1378.097,
        1377.43,
        1376.597,
        1375.93,
        1375.264,
        1374.597,
        1372.764,
        1371.597,
        1370.93,
        1370.93,
        1371.597,
        1373.43,
        1375.43,
        1376.597,
        1377.264,
        1378.264,
        1378.93,
        1379.764,
        1380.93,
        1382.43,
        1383.264,
        1383.93,
        1384.764,
        1384.93,
        1385.764,
        1387.097,
        1388.097,
        1390.264,
        1392.597,
        1395.93,
        1397.93,
        1399.93,
        1402.264,
        1404.097,
        1404.597,
        1404.597,
        1403.43,
        1401.097,
        1397.764
      ],
      "y": [
        474.996,
        478.996,
        483.83,
        488.496,
        493.663,
        498.163,
        502.496,
        507.496,
        512.33,
        517.996,
        524.33,
        530.496,
        537.496,
        545.83,
        551.33,
        556.496,
        561.163,
        565.163,
        572.496,
        578.996,
        585.33,
        590.496,
        594.33,
        598.163,
        600.163,
        598.163,
        595.33,
        591.663,
        588.163,
        582.163,
        576.33,
        569.663,
        562.83,
        556.996,
        549.163,
        542.496,
        536.163,
        530.996,
        524.83,
        519.663,
        514.83,
        510.83,
        505.33,
        501.663,
        498.496,
        494.163,
        488.83,
        485.33,
        479.663,
        475.33,
        472.663,
        470.663
      ]
    }
  ]
}