{
  "data": [
    {
      "x": [
        699.079,
        696.745,
        696.245,
        696.079,
        695.579,
        694.412,
        693.745,
        693.245,
        693.079,
        693.079,
        693.079,
        692.579,
        692.579,
        692.245,
        692.245,
        692.079,
        692.245,
        693.079,
        693.579,
        694.745,
        695.912,
        696.745,
        697.245,
        698.245,
        699.412,
        699.745,
        700.079,
        699.245,
        698.912,
        698.079,
        696.745,
        694.412,
        692.579,
        690.245,
        688.912,
        688.579,
        688.412,
        688.412,
        689.079,
        690.079,
        690.579,
        691.412,
        692.579,
        694.079,
        696.912,
        698.079,
        699.412,
        702.079,
        703.245,
        703.579,
        704.079,
        704.079,
        704.079,
        703.079,
        701.912,
        700.412,
        699.412,
        698.912,
        698.245,
        697.579,
        696.912,
        696.745,
        697.079,
        698.079,
        698.412,
        698.912,
        699.745,
        700.579,
        700.579,
        700.579,
        699.579
      ],
      "y": [
        622.87,
        620.37,
        618.037,
        615.87,
        613.537,
        610.703,
        607.537,
        604.87,
        601.037,
        598.537,
        595.203,
        591.87,
        589.203,
        585.37,
        583.203,
        578.703,
        574.37,
        569.203,
        566.703,
        563.037,
        557.37,
        553.703,
        550.537,
        546.703,
        543.037,
        540.037,
        538.037,
        533.203,
        528.87,
        525.37,
        522.703,
        518.037,
        514.37,
        510.203,
        507.703,
        503.703,
        500.537,
        497.37,
        495.537,
        496.703,
        500.037,
        503.703,
        507.37,
        509.87,
        514.37,
        516.537,
        519.203,
        524.703,
        528.87,
        532.537,
        537.37,
        542.37,
        546.203,
        549.703,
        553.703,
        559.037,
        563.703,
        568.703,
        574.203,
        577.87,
        581.87,
        586.037,
        590.37,
        594.537,
        597.537,
        602.203,
        605.87,
        611.703,
        615.87,
        618.537,
        622.37
      ]
    },
    {
      "x": [
        715.412,
        716.079,
        719.245,
        721.412,
        726.412,
        730.745,
        735.079,
        740.245,
        745.245,
        750.412,
        755.079,
        758.912,
        762.245,
        766.745,
        770.412,
        776.412,
        781.412,
        785.412,
        790.412,
        795.245,
        800.412,
        805.412,
        809.079,
        813.412,
        816.579,
        820.912,
        825.245,
        828.912,
        832.412,
        830.579,
        827.245,
        822.745,
        817.745,
        813.579,
        810.079,
        808.245,
        804.245,
        801.412,
        798.245,
        794.579,
        790.745,
        787.245,
        782.579,
        779.412,
        775.745,
        771.745,
        767.245,
        764.245,
        761.245,
        758.079,
        753.745,
        750.079,
        746.079,
        742.412,
        739.245,
        736.245,
        732.912,
        730.079,
        727.412,
        725.079,
        721.912,
        720.245,
        717.579,
        715.912
      ],
      "y": [
        194.988,
        193.321,
        191.654,
        190.988,
        189.654,
        188.321,
        187.321,
        186.488,
        184.488,
        183.154,
        181.488,
        179.654,
        178.321,
        174.988,
        171.988,
        167.821,
        164.654,
        162.988,
        160.321,
        158.321,
        157.321,
        157.321,
        157.488,
        159.988,
        161.321,
        160.988,
        161.321,
        161.321,
        161.154,
        161.821,
        162.821,
        162.821,
        162.821,
        162.821,
        160.988,
        160.488,
        160.488,
        160.654,
        161.821,
        162.321,
        164.488,
        166.321,
        168.821,
        171.321,
        173.654,
        176.654,
        180.154,
        182.154,
        183.488,
        185.488,
        186.988,
        187.988,
        188.654,
        189.988,
        190.654,
        191.821,
        192.154,
        192.821,
        193.488,
        194.321,
        194.988,
        195.154,
        194.821,
        195.154
      ]
    }
  ]
}