{
  "data": [
    {
      "x": [
        548.346,
        552.679,
        557.679,
        561.346,
        567.512,
        574.512,
        582.512,
        589.679,
        597.846,
        605.012,
        613.012,
        621.346,
        629.179,
        637.346,
        645.846,
        654.346,
        663.346,
        669.512,
        674.346,
        681.012,
        686.179,
        691.846,
        695.346,
        698.012,
        696.679,
        694.179,
        689.012,
        681.846,
        673.512,
        666.179,
        658.012,
        647.679,
        639.012,
        628.179,
        619.179,
        610.346,
        602.179,
        595.512,
        589.012,
        582.346,
        576.846,
        571.346,
        564.512,
        557.846,
        553.846,
        548.512,
        546.346,
        544.346,
        543.346,
        542.679,
        544.512,
        546.179
      ],
      "y": [
        700.764,
        708.598,
        716.598,
        721.598,
        727.598,
        731.598,
        734.098,
        733.431,
        732.098,
        729.431,
        725.931,
        722.431,
        719.931,
        717.431,
        715.598,
        714.931,
        713.931,
        713.098,
        712.098,
        713.431,
        714.264,
        715.764,
        717.764,
        720.764,
        723.764,
        724.931,
        724.764,
        724.431,
        723.598,
        723.764,
        724.931,
        726.431,
        727.431,
        730.598,
        734.098,
        738.098,
        740.931,
        741.931,
        742.598,
        742.264,
        740.598,
        738.264,
        734.598,
        730.264,
        726.598,
        721.764,
        716.764,
        709.931,
        702.931,
        697.264,
        696.431,
        698.598
      ]
    },
    {
      "x": [
        756.972,
        751.472,
        746.972,
        741.472,
        737.138,
        732.972,
        730.972,
        728.472,
        726.472,
        725.805,
        725.805,
        727.972,
        730.305,
        734.805,
        739.805,
        745.138,
        751.138,
        757.472,
        761.972,
        766.638,
        771.472,
        776.305,
        781.638,
        786.972,
        793.638,
        801.805,
        809.138,
        816.472,
        823.972,
        830.638,
        835.638,
        839.305,
        842.638,
        845.972,
        847.638,
        849.472,
        851.138,
        852.805,
        856.138,
        858.805,
        860.972,
        860.138,
        857.805,
        854.472,
        851.305,
        849.472,
        848.305,
        847.472,
        844.972,
        842.972,
        840.472,
        838.305,
        835.638,
        830.138,
        819.805,
        809.138,
        800.472,
        791.138,
        784.472,
        778.805,
        772.972,
        768.138,
        762.972
      ],
      "y": [
        355.13,
        361.464,
        366.964,
        372.464,
        376.797,
        381.13,
        384.797,
        389.964,
        394.297,
        398.63,
        399.297,
        400.797,
        399.464,
        395.63,
        390.964,
        385.464,
        379.797,
        372.63,
        366.964,
        360.63,
        354.13,
        348.297,
        342.464,
        336.464,
        330.797,
        324.63,
        320.297,
        315.13,
        309.464,
        303.63,
        299.297,
        294.464,
        290.13,
        283.297,
        275.297,
        266.297,
        258.63,
        250.797,
        243.13,
        238.464,
        234.797,
        232.464,
        231.63,
        232.797,
        237.13,
        242.63,
        247.63,
        253.464,
        262.464,
        269.464,
        275.964,
        281.297,
        285.797,
        292.297,
        300.297,
        307.297,
        312.797,
        319.464,
        324.797,
        329.797,
        335.63,
        340.797,
        346.63
      ]
    },
    {
      "x": [
        1237.15,
        1229.817,
        1222.984,
        1215.317,
        1208.15,
        1201.984,
        1195.817,
        1190.317,
        1184.984,
        1181.317,
        1177.65,
        1175.65,
        1174.65,
        1176.15,
        1179.15,
        1182.984,
        1186.984,
        1190.984,
        1196.15,
        1200.817,
        1206.484,
        1210.984,
        1215.817,
        1222.317,
        1228.65,
        1235.65,
        1243.15,
        1251.317,
        1259.317,
        1267.484,
        1275.984,
        1284.65,
        1294.984,
        1304.317,
        1312.484,
        1319.984,
        1326.317,
        1331.484,
        1335.984,
        1336.65,
        1336.317,
        1333.484,
        1328.65,
        1321.817,
        1316.15,
        1307.484,
        1298.317,
        1290.484,
        1280.317,
        1269.817,
        1260.317,
        1253.15,
        1245.317
      ],
      "y": [
        665.183,
        662.85,
        659.683,
        655.016,
        652.183,
        649.183,
        647.016,
        646.35,
        646.35,
        647.35,
        649.35,
        651.35,
        653.183,
        654.35,
        654.683,
        653.35,
        651.683,
        651.516,
        652.183,
        653.85,
        657.183,
        660.683,
        664.016,
        667.516,
        670.516,
        673.016,
        674.183,
        674.183,
        673.683,
        672.016,
        670.516,
        670.516,
        670.516,
        671.85,
        673.683,
        675.183,
        675.35,
        675.183,
        673.85,
        673.016,
        670.85,
        669.016,
        667.183,
        665.35,
        663.516,
        662.85,
        662.35,
        662.183,
        662.183,
        663.35,
        664.683,
        665.516,
        665.85
      ]
    }
  ]
}