{
  "data": [
    {
      "x": [
        816.243,
        810.261,
        805.026,
        802.534,
        802.035,
        804.528,
        811.507,
        818.736,
        824.469,
        830.202,
        834.938,
        839.675,
        843.414,
        849.645,
        856.375,
        863.853,
        873.824,
        886.287,
        899.499,
        912.46,
        923.927,
        932.402,
        936.889,
        944.865,
        954.836,
        960.818,
        962.563,
        960.818,
        954.836,
        947.607,
        939.88,
        928.414,
        917.695,
        905.98,
        895.012,
        884.293,
        874.821,
        866.346,
        858.12,
        851.639,
        844.909,
        838.927,
        832.695,
        826.214,
        821.727
      ],
      "y": [
        839.115,
        838.118,
        838.118,
        839.115,
        842.106,
        843.851,
        843.851,
        844.848,
        847.59,
        851.827,
        856.813,
        863.792,
        869.525,
        875.757,
        880.742,
        884.481,
        887.473,
        889.467,
        890.713,
        891.212,
        891.71,
        892.458,
        895.2,
        897.443,
        898.191,
        897.693,
        895.449,
        892.957,
        890.215,
        888.22,
        886.226,
        883.983,
        882.986,
        882.737,
        882.487,
        881.49,
        879.995,
        876.256,
        871.769,
        866.534,
        859.305,
        853.323,
        847.091,
        842.854,
        840.86
      ]
    },
    {
      "x": [
        1229.824,
        1226.085,
        1223.094,
        1220.851,
        1218.358,
        1216.364,
        1221.848,
        1225.338,
        1229.575,
        1233.813,
        1238.05,
        1245.03,
        1253.505,
        1262.229,
        1276.188,
        1288.153,
        1299.37,
        1309.59,
        1319.311,
        1330.528,
        1339.502,
        1346.731,
        1353.71,
        1361.936,
        1368.915,
        1374.898,
        1380.132,
        1383.871,
        1386.115,
        1385.367,
        1380.88,
        1373.153,
        1365.176,
        1356.951,
        1350.47,
        1342.493,
        1335.264,
        1327.537,
        1319.81,
        1312.83,
        1305.352,
        1297.874,
        1288.651,
        1277.684,
        1265.47,
        1256.745,
        1248.519,
        1240.543,
        1235.308
      ],
      "y": [
        598.786,
        604.021,
        609.754,
        615.986,
        620.971,
        623.962,
        623.962,
        619.226,
        610.252,
        604.021,
        599.783,
        595.296,
        592.305,
        590.81,
        590.56,
        590.311,
        589.065,
        586.323,
        580.59,
        570.868,
        561.645,
        553.42,
        546.191,
        537.467,
        532.98,
        527.994,
        522.012,
        516.03,
        509.798,
        507.804,
        509.05,
        512.291,
        516.777,
        523.258,
        530.736,
        539.211,
        548.185,
        557.906,
        566.382,
        572.364,
        576.352,
        578.845,
        580.839,
        581.587,
        582.833,
        584.079,
        586.572,
        590.56,
        593.801
      ]
    },
    {
      "x": [
        696.4,
        696.649,
        695.902,
        696.4,
        698.893,
        702.133,
        705.124,
        707.866,
        708.614,
        708.614,
        706.869,
        704.626,
        703.38,
        701.136,
        698.145,
        694.157,
        690.418,
        688.424,
        687.676,
        688.424,
        689.919,
        692.163,
        695.652,
        698.644,
        701.385,
        702.383,
        701.385,
        699.391,
        696.649,
        694.655,
        693.409,
        691.415,
        687.676,
        684.186,
        681.195,
        679.45,
        678.951,
        680.198,
        683.189,
        686.18,
        689.421,
        692.412,
        694.905
      ],
      "y": [
        279.207,
        284.94,
        289.926,
        294.412,
        300.893,
        307.125,
        309.867,
        306.876,
        299.896,
        291.67,
        283.943,
        276.465,
        266.993,
        256.025,
        244.808,
        234.588,
        225.365,
        218.137,
        209.163,
        200.19,
        189.72,
        179.75,
        169.28,
        161.304,
        153.577,
        147.096,
        143.357,
        145.102,
        150.087,
        155.571,
        161.304,
        165.791,
        172.521,
        181.245,
        190.967,
        200.937,
        210.409,
        220.879,
        230.102,
        239.574,
        251.289,
        262.506,
        271.48
      ]
    }
  ]
}