{
  "data": [
    {
      "x": [
        743.227,
        746.061,
        748.727,
        751.727,
        754.727,
        757.727,
        760.394,
        763.561,
        767.061,
        769.894,
        771.061,
        775.061,
        778.727,
        782.727,
        785.227,
        786.727,
        787.394,
        785.727,
        783.894,
        783.061,
        780.061,
        776.394,
        772.894,
        770.561,
        768.061,
        765.394,
        762.894,
        759.727,
        756.061,
        753.394,
        749.894,
        746.727,
        743.894,
        740.394,
        737.227,
        733.394,
        727.878,
        722.378,
        718.211,
        715.878,
        713.545,
        711.378,
        709.211,
        708.378,
        707.545,
        707.045,
        706.545,
        705.878,
        705.045,
        703.711,
        703.711,
        703.711,
        704.711,
        707.045,
        711.211,
        714.878,
        718.878,
        723.878,
        728.211,
        731.378,
        734.211,
        737.378,
        739.878,
        741.545
      ],
      "y": [
        811.556,
        818.556,
        825.056,
        831.89,
        837.056,
        841.89,
        848.556,
        854.056,
        860.056,
        865.056,
        867.89,
        873.056,
        877.89,
        880.556,
        879.89,
        878.723,
        874.39,
        870.723,
        867.556,
        864.056,
        862.556,
        857.39,
        851.89,
        846.723,
        841.723,
        835.39,
        829.89,
        824.056,
        817.723,
        811.056,
        803.89,
        798.723,
        794.223,
        789.89,
        786.723,
        782.89,
        778.223,
        773.723,
        769.39,
        765.556,
        761.056,
        756.056,
        748.723,
        743.723,
        738.89,
        734.39,
        728.723,
        735.056,
        741.056,
        746.223,
        751.39,
        756.39,
        761.39,
        765.89,
        771.723,
        776.723,
        781.556,
        786.723,
        791.056,
        794.223,
        797.39,
        800.556,
        804.056,
        807.39
      ]
    },
    {
      "x": [
        1374.948,
        1371.115,
        1367.282,
        1362.115,
        1357.615,
        1352.948,
        1349.615,
        1344.448,
        1339.782,
        1334.282,
        1325.948,
        1319.782,
        1313.282,
        1306.448,
        1299.948,
        1292.282,
        1288.448,
        1284.115,
        1279.948,
        1277.282,
        1278.282,
        1281.948,
        1284.782,
        1287.615,
        1291.448,
        1296.282,
        1298.448,
        1302.615,
        1306.115,
        1310.282,
        1316.782,
        1322.448,
        1327.115,
        1332.615,
        1336.282,
        1342.282,
        1345.948,
        1351.448,
        1357.115,
        1360.615,
        1365.782,
        1372.948,
        1378.115,
        1383.448,
        1392.448,
        1398.782,
        1403.115,
        1409.818,
        1413.651,
        1417.318,
        1417.985,
        1416.151,
        1411.651,
        1403.485,
        1398.151,
        1390.318,
        1384.151,
        1379.818
      ],
      "y": [
        306.39,
        308.223,
        310.223,
        313.89,
        318.056,
        323.056,
        327.556,
        334.556,
        340.89,
        345.556,
        353.056,
        359.056,
        363.723,
        368.556,
        373.056,
        377.723,
        381.056,
        383.056,
        384.223,
        383.556,
        379.223,
        373.89,
        370.39,
        367.723,
        364.89,
        362.39,
        362.056,
        359.056,
        355.89,
        352.223,
        347.39,
        342.056,
        336.89,
        330.556,
        325.556,
        320.556,
        317.223,
        311.89,
        307.056,
        304.89,
        301.556,
        299.39,
        298.39,
        297.556,
        297.556,
        297.39,
        297.223,
        297.39,
        296.89,
        294.556,
        297.223,
        300.89,
        303.39,
        303.723,
        303.723,
        303.723,
        303.89,
        304.056
      ]
    },
    {
      "x": [
        1306.818,
        1313.818,
        1321.485,
        1327.651,
        1333.485,
        1338.485,
        1343.985,
        1348.151,
        1353.151,
        1357.818,
        1362.651,
        1366.318,
        1369.651,
        1373.985,
        1379.651,
        1379.485,
        1376.818,
        1373.318,
        1368.818,
        1366.151,
        1363.485,
        1358.485,
        1353.318,
        1348.485,
        1343.318,
        1338.985,
        1334.151,
        1330.485,
        1326.818,
        1323.151,
        1317.651,
        1313.151,
        1308.485,
        1305.818,
        1300.745,
        1296.912,
        1293.079,
        1289.912,
        1286.245,
        1283.245,
        1279.079,
        1275.912,
        1272.579,
        1269.079,
        1265.412,
        1260.912,
        1257.579,
        1254.245,
        1251.412,
        1248.745,
        1247.079,
        1246.912,
        1249.745,
        1252.079,
        1258.079,
        1263.579,
        1267.412,
        1272.579,
        1280.245,
        1286.912,
        1291.912,
        1297.245,
        1302.079
      ],
      "y": [
        52.223,
        56.556,
        59.556,
        62.223,
        64.556,
        66.056,
        67.89,
        69.89,
        71.39,
        72.723,
        75.39,
        78.556,
        81.723,
        85.39,
        89.056,
        85.223,
        80.39,
        76.89,
        72.89,
        70.223,
        68.723,
        66.723,
        64.056,
        62.39,
        60.723,
        59.723,
        58.39,
        56.89,
        55.39,
        53.89,
        51.056,
        48.556,
        45.39,
        42.89,
        40.333,
        37.333,
        34.833,
        32.5,
        30.5,
        28.5,
        25.333,
        22.833,
        20.0,
        20.0,
        17.333,
        16.0,
        15.0,
        13.667,
        13.167,
        12.5,
        13.833,
        16.333,
        19.5,
        20.833,
        23.167,
        25.5,
        28.667,
        32.0,
        36.5,
        40.833,
        43.667,
        46.5,
        49.833
      ]
    }
  ]
}