{
  "data": [
    {
      "x": [
        665.939,
        663.908,
        661.587,
        659.267,
        657.526,
        654.915,
        653.755,
        653.464,
        653.755,
        654.915,
        655.785,
        656.075,
        656.656,
        656.365,
        655.785,
        654.915,
        654.045,
        652.884,
        652.014,
        650.563,
        649.983,
        648.823,
        647.082,
        646.212,
        644.181,
        641.86,
        640.41,
        640.41,
        639.54,
        639.83,
        642.15,
        643.891,
        645.342,
        647.082,
        647.953,
        648.533,
        649.113,
        649.693,
        649.693,
        649.403,
        649.403,
        649.403,
        649.113,
        648.533,
        648.243,
        648.823,
        649.983,
        651.434,
        653.755,
        656.946,
        659.847,
        662.168,
        663.618,
        665.939
      ],
      "y": [
        645.713,
        649.194,
        650.645,
        653.256,
        657.027,
        661.379,
        666.31,
        671.242,
        677.624,
        684.587,
        690.389,
        696.481,
        702.283,
        706.634,
        711.856,
        717.948,
        723.751,
        729.843,
        734.774,
        739.706,
        744.638,
        749.28,
        753.341,
        757.402,
        760.884,
        764.075,
        761.754,
        757.983,
        753.921,
        749.86,
        745.218,
        740.286,
        734.194,
        729.262,
        723.751,
        718.819,
        713.017,
        706.925,
        701.413,
        695.32,
        690.969,
        685.167,
        679.075,
        674.143,
        668.921,
        664.57,
        660.508,
        657.027,
        654.126,
        650.935,
        647.744,
        645.713,
        643.972,
        643.102
      ]
    },
    {
      "x": [
        830.243,
        829.373,
        827.052,
        824.731,
        822.41,
        820.67,
        818.929,
        818.059,
        816.898,
        816.028,
        816.028,
        817.478,
        818.639,
        820.089,
        821.83,
        823.571,
        825.311,
        827.342,
        828.212,
        828.502,
        828.502,
        829.373,
        828.792,
        827.922,
        827.922,
        826.762,
        825.601,
        825.021,
        823.28,
        820.96,
        821.25,
        820.96,
        821.25,
        821.83,
        822.41,
        822.41,
        822.12,
        822.12,
        821.54,
        820.379,
        818.929,
        817.188,
        815.738,
        813.707,
        812.837,
        811.676,
        810.806,
        810.516,
        810.226,
        811.386,
        812.837,
        815.158,
        817.769,
        820.379,
        823.28,
        826.472
      ],
      "y": [
        544.662,
        546.983,
        549.884,
        553.075,
        556.267,
        559.748,
        563.519,
        567.0,
        572.802,
        578.024,
        583.536,
        589.918,
        595.14,
        601.232,
        607.615,
        613.707,
        619.509,
        625.601,
        631.113,
        636.915,
        642.717,
        651.42,
        657.222,
        662.154,
        667.086,
        671.727,
        676.949,
        680.14,
        683.331,
        682.461,
        678.11,
        672.888,
        668.246,
        663.024,
        657.222,
        650.84,
        644.458,
        637.205,
        631.113,
        625.601,
        619.799,
        612.837,
        607.905,
        600.652,
        594.56,
        589.628,
        584.697,
        580.635,
        574.833,
        570.191,
        564.97,
        560.328,
        555.106,
        551.335,
        547.854,
        544.953
      ]
    }
  ]
}