{
  "data": [
    {
      "x": [
        690.315,
        692.212,
        696.005,
        701.549,
        706.656,
        712.491,
        717.89,
        724.601,
        730.291,
        736.856,
        742.546,
        747.361,
        752.759,
        756.406,
        759.616,
        762.971,
        766.181,
        769.974,
        773.768,
        778.582,
        784.418,
        789.524,
        792.297,
        793.61,
        792.297,
        789.67,
        785.148,
        780.187,
        774.643,
        770.12,
        765.598,
        761.95,
        757.865,
        754.801,
        751.154,
        746.777,
        742.984,
        737.731,
        732.333,
        726.789,
        722.121,
        717.014,
        711.616,
        706.364,
        701.112,
        697.172,
        693.525
      ],
      "y": [
        277.114,
        274.925,
        272.591,
        269.819,
        267.922,
        266.317,
        265.588,
        265.296,
        265.296,
        265.734,
        267.047,
        268.943,
        271.715,
        274.779,
        277.843,
        281.49,
        284.554,
        287.618,
        290.39,
        291.849,
        291.12,
        289.223,
        288.785,
        290.098,
        291.849,
        293.6,
        294.913,
        295.351,
        294.329,
        292.287,
        289.223,
        286.451,
        282.366,
        279.156,
        275.946,
        272.737,
        271.278,
        270.111,
        269.819,
        269.819,
        270.111,
        270.548,
        271.278,
        272.445,
        274.633,
        276.384,
        277.114
      ]
    },
    {
      "x": [
        1210.517,
        1208.621,
        1207.308,
        1206.578,
        1205.849,
        1205.411,
        1205.411,
        1206.14,
        1206.87,
        1207.745,
        1209.058,
        1210.517,
        1212.414,
        1213.873,
        1214.748,
        1215.04,
        1215.186,
        1214.748,
        1213.143,
        1211.247,
        1209.058,
        1206.724,
        1205.119,
        1204.39,
        1203.952,
        1204.244,
        1204.827,
        1206.286,
        1206.87,
        1206.724,
        1206.578,
        1206.578,
        1207.162,
        1208.183,
        1209.642,
        1211.83,
        1214.165,
        1215.915,
        1217.52,
        1218.979,
        1219.855,
        1219.563,
        1218.687,
        1217.52,
        1216.061,
        1214.456,
        1213.289,
        1212.122,
        1211.247,
        1210.663,
        1210.517,
        1210.517,
        1210.809,
        1210.809,
        1210.955
      ],
      "y": [
        617.941,
        615.46,
        611.521,
        606.707,
        601.746,
        596.202,
        591.096,
        585.698,
        580.591,
        575.923,
        569.211,
        564.251,
        559.436,
        554.622,
        549.515,
        545.139,
        539.594,
        535.218,
        530.111,
        525.005,
        519.899,
        514.792,
        508.665,
        503.558,
        498.598,
        493.929,
        490.136,
        487.072,
        490.719,
        495.096,
        498.598,
        502.245,
        506.622,
        510.123,
        514.063,
        518.731,
        523.108,
        527.485,
        531.424,
        536.677,
        542.221,
        547.765,
        553.017,
        557.831,
        562.208,
        567.898,
        573.005,
        577.673,
        583.071,
        588.032,
        592.846,
        598.536,
        604.226,
        609.916,
        614.439
      ]
    },
    {
      "x": [
        715.234,
        717.568,
        721.07,
        725.301,
        729.823,
        735.367,
        741.933,
        747.915,
        753.459,
        759.294,
        765.568,
        771.841,
        777.386,
        782.784,
        787.452,
        791.392,
        795.622,
        799.708,
        803.793,
        807.878,
        812.109,
        816.486,
        819.112,
        815.027,
        810.796,
        806.565,
        803.209,
        799.27,
        795.039,
        790.516,
        786.285,
        782.492,
        778.115,
        773.3,
        767.756,
        762.212,
        756.522,
        751.416,
        745.434,
        740.182,
        734.054,
        727.781,
        722.675,
        718.006
      ],
      "y": [
        632.498,
        630.31,
        629.143,
        628.267,
        627.83,
        627.538,
        627.246,
        627.392,
        627.538,
        627.392,
        627.392,
        627.83,
        628.851,
        631.039,
        633.811,
        636.292,
        639.064,
        642.127,
        645.191,
        648.547,
        651.757,
        654.674,
        657.009,
        656.425,
        654.529,
        652.048,
        649.422,
        646.213,
        643.295,
        640.231,
        637.896,
        635.27,
        632.936,
        631.915,
        631.331,
        631.477,
        632.061,
        632.644,
        632.936,
        633.228,
        633.52,
        633.811,
        634.249,
        633.811
      ]
    }
  ]
}