{
  "data": [
    {
      "x": [
        638.858,
        634.152,
        630.858,
        626.152,
        622.152,
        618.858,
        615.564,
        612.976,
        612.27,
        614.152,
        616.505,
        620.741,
        626.388,
        632.27,
        637.211,
        641.211,
        645.211,
        650.152,
        655.329,
        660.976,
        665.917,
        670.623,
        673.991,
        674.586,
        674.747,
        673.335,
        672.976,
        672.035,
        671.8,
        672.035,
        672.035,
        670.388,
        668.27,
        665.211,
        660.27,
        654.388,
        648.741,
        644.505
      ],
      "y": [
        478.445,
        483.386,
        488.092,
        494.445,
        499.622,
        504.092,
        508.327,
        512.563,
        516.798,
        518.21,
        516.327,
        511.622,
        503.857,
        495.622,
        489.504,
        484.798,
        479.857,
        475.857,
        471.622,
        466.68,
        462.21,
        456.092,
        448.662,
        442.94,
        435.969,
        428.327,
        425.504,
        429.504,
        432.563,
        437.269,
        442.445,
        446.916,
        451.857,
        457.739,
        462.21,
        466.68,
        471.857,
        474.445
      ]
    },
    {
      "x": [
        683.329,
        680.741,
        679.564,
        679.329,
        677.682,
        676.976,
        676.27,
        674.623,
        673.211,
        670.858,
        670.858,
        671.564,
        672.27,
        673.211,
        673.682,
        674.858,
        677.818,
        680.716,
        685.954,
        689.744,
        694.152,
        699.564,
        704.976,
        712.27,
        717.917,
        723.564,
        727.094,
        733.682,
        736.741,
        739.329,
        734.388,
        730.388,
        725.211,
        722.858,
        719.094,
        713.682,
        711.094,
        706.858,
        700.976,
        698.152,
        695.094,
        692.27,
        690.388,
        688.035,
        685.917
      ],
      "y": [
        557.504,
        551.857,
        546.916,
        540.327,
        533.269,
        527.386,
        523.386,
        519.151,
        515.857,
        515.151,
        518.21,
        522.916,
        529.269,
        536.092,
        542.445,
        549.504,
        557.058,
        563.881,
        569.133,
        572.947,
        576.798,
        578.445,
        579.151,
        580.563,
        582.445,
        584.327,
        585.504,
        585.975,
        585.975,
        582.68,
        580.092,
        578.445,
        577.033,
        576.563,
        576.092,
        574.916,
        574.68,
        573.975,
        571.857,
        571.386,
        569.269,
        567.622,
        566.21,
        564.327,
        562.21
      ]
    },
    {
      "x": [
        810.273,
        804.391,
        795.685,
        789.802,
        782.979,
        775.685,
        771.214,
        766.273,
        762.508,
        759.214,
        762.038,
        767.92,
        774.273,
        782.508,
        789.097,
        796.391,
        800.861,
        806.038,
        810.979,
        816.861,
        823.214,
        827.92,
        833.332,
        839.214,
        843.214,
        848.081,
        851.449,
        857.567,
        862.038,
        866.273,
        871.635,
        878.31,
        882.508,
        887.685,
        890.508,
        887.685,
        885.097,
        881.567,
        878.979,
        874.744,
        872.391,
        868.155,
        865.332,
        859.92,
        855.92,
        850.744,
        846.508,
        842.508,
        835.92,
        830.273,
        824.861,
        820.391
      ],
      "y": [
        257.47,
        255.822,
        252.999,
        251.822,
        251.117,
        250.411,
        249.94,
        249.47,
        249.234,
        249.705,
        252.764,
        255.822,
        256.764,
        257.47,
        257.94,
        259.587,
        260.293,
        262.411,
        263.822,
        266.646,
        269.94,
        273.705,
        277.234,
        279.352,
        280.528,
        281.99,
        282.881,
        282.881,
        282.646,
        281.234,
        278.769,
        277.036,
        276.937,
        277.705,
        276.528,
        274.881,
        274.411,
        274.411,
        274.411,
        274.881,
        275.587,
        276.528,
        277.47,
        278.175,
        279.117,
        278.411,
        276.999,
        274.881,
        272.058,
        267.587,
        264.058,
        261.94
      ]
    }
  ]
}